desync_data/__init__.py
desync_data/core.py
desync_data/utils.py
desync_data-0.1.3.dist-info/METADATA
desync_data-0.1.3.dist-info/WHEEL
desync_data-0.1.3.dist-info/top_level.txt
desync_data-0.1.3.dist-info/RECORD
