Metadata-Version: 2.4
Name: desync-data
Version: 0.1.3
Summary: Utility tools for Desync AI users
Author: Jackson Ballow
Classifier: Programming Language :: Python :: 3
Requires-Python: >=3.7
Requires-Dist: desync_search
Requires-Dist: beautifulsoup4
Dynamic: author
Dynamic: classifier
Dynamic: description
Dynamic: description-content-type
Dynamic: requires-dist
Dynamic: requires-python
Dynamic: summary
